tbm13_utils/__init__.py
tbm13_utils/all.py
tbm13_utils/display.py
tbm13_utils/encoding.py
tbm13_utils/environment.py
tbm13_utils/flow.py
tbm13_utils/input.py
tbm13_utils/net.py
tbm13_utils/settings.py
tbm13_utils-1.1.dist-info/LICENSE
tbm13_utils-1.1.dist-info/METADATA
tbm13_utils-1.1.dist-info/WHEEL
tbm13_utils-1.1.dist-info/top_level.txt
tbm13_utils-1.1.dist-info/RECORD
