Metadata-Version: 2.1
Name: tbm13_utils
Version: 1.1
Summary: Utils made for personal use
Author-email: TBM13 <mateo.trueba@gmail.com>
Project-URL: Homepage, https://github.com/TBM13/tbm13-utils
Project-URL: Bug Tracker, https://github.com/TBM13/tbm13-utils/issues
Classifier: Programming Language :: Python :: 3
Classifier: Programming Language :: Python :: 3.10
Classifier: Intended Audience :: Developers
Classifier: License :: OSI Approved :: MIT License
Classifier: Operating System :: OS Independent
Classifier: Topic :: Utilities
Requires-Python: >=3.10
License-File: LICENSE
Requires-Dist: requests
